owl_ab_test/__init__.py
owl_ab_test/core.py
owl_ab_test/exceptions.py
tests/__init__.py
tests/test_core.py
owl_ab_test-0.1.9.dist-info/LICENSE
owl_ab_test-0.1.9.dist-info/METADATA
owl_ab_test-0.1.9.dist-info/WHEEL
owl_ab_test-0.1.9.dist-info/top_level.txt
owl_ab_test-0.1.9.dist-info/RECORD
