Metadata-Version: 2.2
Name: owl_ab_test
Version: 0.1.9
Summary: A Python package for A/B testing statistical analysis
Home-page: https://github.com/anika-academia/owl_ab_test
Author: owl_ab_test
Author-email: Anika Ranginani <anika.ranginani@gmail.com>
License: MIT
Project-URL: Homepage, https://github.com/anika-academia/owl_ab_test
Project-URL: Bug Tracker, https://github.com/anika-academia/owl_ab_test/issues
Requires-Python: >=3.7
License-File: LICENSE
Dynamic: author
Dynamic: home-page
Dynamic: requires-python
